genens/.logging_config.json
genens/__init__.py
genens/base.py
genens/genens.py
genens/log_utils.py
genens/config/__init__.py
genens/config/config_clf.yaml
genens/config/config_default.yaml
genens/config/config_templates.py
genens/config/genens_config.py
genens/config/utils.py
genens/gp/__init__.py
genens/gp/crossover.py
genens/gp/evolution.py
genens/gp/mutation.py
genens/gp/tree.py
genens/gp/types.py
genens/render/__init__.py
genens/render/graph.py
genens/render/plot.py
genens/tests/__init__.py
genens/tests/check_operators.py
genens/tests/gen_boxplot.py
genens/tests/load_datasets.py
genens/tests/process_results.py
genens/tests/run_datasets.py
genens/tests/run_openml.py
genens/tests/settings_test.py
genens/workflow/__init__.py
genens/workflow/builtins.py
genens/workflow/evaluate.py
genens/workflow/model_creation.py
tests/__init__.py
genens-0.1.16.dist-info/LICENSE
genens-0.1.16.dist-info/METADATA
genens-0.1.16.dist-info/WHEEL
genens-0.1.16.dist-info/top_level.txt
genens-0.1.16.dist-info/RECORD
