Metadata-Version: 2.1
Name: genens
Version: 0.1.16
Summary: A genetic AutoML system for ensemble methods
Home-page: https://github.com/gabrielasuchopar/genens
Author: Gabriela Suchoparova
Author-email: gabi.suchoparova@gmail.com
License: UNKNOWN
Platform: UNKNOWN
Classifier: Programming Language :: Python :: 3.6
Classifier: Programming Language :: Python :: 3.7
Classifier: License :: OSI Approved :: MIT License
Classifier: Operating System :: OS Independent
Requires-Python: >=3.6
Requires-Dist: deap
Requires-Dist: joblib
Requires-Dist: openml
Requires-Dist: matplotlib
Requires-Dist: numpy
Requires-Dist: scikit-learn (>=0.22)
Requires-Dist: seaborn
Requires-Dist: stopit
Requires-Dist: pyyaml
